pre_commit_taskid/__init__.py
pre_commit_taskid-0.1.2.dist-info/METADATA
pre_commit_taskid-0.1.2.dist-info/WHEEL
pre_commit_taskid-0.1.2.dist-info/entry_points.txt
pre_commit_taskid-0.1.2.dist-info/RECORD
