Metadata-Version: 2.4
Name: pre-commit-taskid
Version: 0.1.2
Summary: A pre-commit hook that automatically appends task IDs from branch names to commit messages
Author-email: saif <sirsaif99@gmail.com>
Requires-Python: >=3.9
Requires-Dist: pre-commit>=4.0.0
Requires-Dist: pytest-cov>=6.0.0
Requires-Dist: pytest>=8.3.5
Provides-Extra: dev
Requires-Dist: black>=23.0.0; extra == 'dev'
Requires-Dist: flake8>=6.0.0; extra == 'dev'
Requires-Dist: isort>=5.0.0; extra == 'dev'
Requires-Dist: pytest-cov>=4.0.0; extra == 'dev'
Requires-Dist: pytest>=7.0.0; extra == 'dev'
